cracknuts_panel/__init__.py
cracknuts_panel/__main__.py
cracknuts_panel/acquisition_panel.py
cracknuts_panel/cracker_panel.py
cracknuts_panel/cracknuts_panel.py
cracknuts_panel/panel.py
cracknuts_panel/trace_analysis_panel.py
cracknuts_panel/trace_panel.py
cracknuts_panel/ui_sync.py
cracknuts_panel/static/AcquisitionPanel.js
cracknuts_panel/static/AcquisitionPanelWidget.js
cracknuts_panel/static/CrackNutsPanelWidget.js
cracknuts_panel/static/CrackerPanel.js
cracknuts_panel/static/CrackerPanelWidget.js
cracknuts_panel/static/TraceAnalysisPanelWidget.js
cracknuts_panel/static/TraceMonitorPanelWidget.js
cracknuts_panel/static/TracePanel.js
cracknuts_panel/template/jupyter/acquisition.ipynb
cracknuts_panel/template/jupyter/analysis.ipynb
cracknuts_panel-0.0.18.dist-info/METADATA
cracknuts_panel-0.0.18.dist-info/WHEEL
cracknuts_panel-0.0.18.dist-info/top_level.txt
cracknuts_panel-0.0.18.dist-info/RECORD
