Metadata-Version: 2.1
Name: cracknuts-panel
Version: 0.0.18
Summary: Noteboot(like jupyter) widget for cracknuts.
Requires-Python: >=3.12
Requires-Dist: anywidget~=0.9.13
Requires-Dist: cracknuts~=0.0.18
Requires-Dist: traitlets~=5.14.3
Requires-Dist: jupyter~=1.1.1
